{"ok":true,"forum":{"name":"help","description":"for all your anyland questions","creatorId":"5773b5232da36d2d18b870fb","creatorName":"philipp","threadCount":346,"latestCommentDate":"2023-12-21T09:35:12.880Z","protectionLevel":0,"creationDate":"2016-12-06T16:31:52.285Z","dialogThingId":"58481eb85a0dc5b20d48e6f8","dialogColor":"255,255,255","latestCommentText":"this is epic!","latestCommentUserId":"622d80e81ee78204797e0e4e","latestCommentUserName":"Captain Crunch","id":"5846f540e8593a971395c0aa","user_isModerator":false,"user_hasFavorited":true},"thread":{"forumId":"5846f540e8593a971395c0aa","title":"i seem to have hit a max object limit fairly quickly","creatorId":"5a778d945a8be3ef2ef6513a","creatorName":"oo","latestCommentDate":"2018-12-30T10:34:19.514Z","commentCount":9,"comments":[{"date":"2018-12-30T10:16:39.173Z","userId":"5a778d945a8be3ef2ef6513a","userName":"oo","text":"is this limit due to computer performance or is there a hard limit?"},{"date":"2018-12-30T10:17:50.660Z","userId":"5a778d945a8be3ef2ef6513a","userName":"oo","text":"reminds me of the issues with manyland when you try to use too many dynamics or very big things in a viewable area."},{"date":"2018-12-30T10:21:27.831Z","userId":"5a778d945a8be3ef2ef6513a","userName":"oo","text":"i built a little hut and instead of creating the entire roof as one mesh, each leaf of the hut roof is its own object. i'm tempted to try to redo it as all one object,"},{"date":"2018-12-30T10:23:01.365Z","userId":"5a778d945a8be3ef2ef6513a","userName":"oo","text":"but i worry i'll spend however many hours redoing it and it'll still have problems and then i'll pretty much rage quit the game."},{"date":"2018-12-30T10:25:20.155Z","userId":"5a778d945a8be3ef2ef6513a","userName":"oo","text":"quick description of the prob: objects are missing as a walk around the hut and only reappear as other objects dissapear."},{"date":"2018-12-30T10:27:56.440Z","userId":"5a483738b91133f0149888b4","userName":"Thifa","text":"you can set show if far away too, or show all, but it will cause lagg"},{"date":"2018-12-30T10:28:38.831Z","userId":"5a483738b91133f0149888b4","userName":"Thifa","text":"try merging , hiding with fog, delete the parts ,that are not visible"},{"date":"2018-12-30T10:29:34.455Z","userId":"5a778d945a8be3ef2ef6513a","userName":"oo","text":"yeah, i've done that for a few objects. that seems to work for them, but i''m not at a very ar distance with my hut. i'm within touching distance of it."},{"date":"2018-12-30T10:34:19.514Z","userId":"5a778d945a8be3ef2ef6513a","userName":"oo","text":"ok, i'll give that a shot. sigh, i hope that works.","likes":["57fa1a9a062bfb6013e320e9"],"oldestLikes":[{"id":"57fa1a9a062bfb6013e320e9","n":"nicolas cage"}],"newestLikes":[],"totalLikes":1}],"isLocked":false,"isSticky":false,"creationDate":"2018-12-30T10:16:39.166Z","latestCommentText":"ok, i'll give that a shot. sigh, i hope that works.","latestCommentUserId":"5a778d945a8be3ef2ef6513a","latestCommentUserName":"oo","id":"5c289b074d67fc6f6091fc54"}}