{"n":"wood","a":[23],"p":[{"t":10,"t1":46,"t2":46,"s":[{"p":[-0.05895047,-0.1451816,0.3256817],"r":[0,0,0],"s":[0.4071248,1.558925,0.01185655],"c":[0.3333331,0.2518516,0.07407377],"b":["when hit then become 2 in 0.5s","when touches bullet 1 then become 2","when touches bb then become 2"],"t1":{"c":[0,0,0],"x":0.5,"y":0.5,"a":0.8925,"m":0,"n":0,"r":0,"g":0,"o":0.5,"t":0.5,"e":0.5},"t2":{"c":[0,0,0],"x":0.5,"y":0.5,"a":0.8925,"m":0,"n":0,"r":0,"g":0,"o":0.5,"t":0.5,"e":0.5}},{"p":[1.099625,-0.2113724,-0.04730558],"r":[0.7682481,271.0328,189.0197],"s":[0.3921989,1.543074,0.01186445],"c":[0.3333332,0.2634919,0.1111109],"b":["when grabbed then become 1 in 0.5s","when starts then play object falling"],"t1":{"c":[0,0,0],"x":0.5,"y":0.5,"a":0.8925,"m":0,"n":0,"r":0,"g":0,"o":0.5,"t":0.5,"e":0.5},"t2":{"c":[0,0,0],"x":0.5,"y":0.5,"a":0.8925,"m":0,"n":0,"r":0,"g":0,"o":0.5,"t":0.5,"e":0.5}}]},{"t":10,"t1":46,"t2":46,"s":[{"p":[-0.4644026,-0.1511507,0.3212603],"r":[9.716058E-06,1.150704E-06,1.366038E-05],"s":[0.4071947,1.559309,0.01185756],"c":[0.3333331,0.2518516,0.07407372],"b":["when hit then become 2 in 0.5s","when touches bullet 1 then become 2","when touches bb then become 2"],"t1":{"c":[0,0,0],"x":0.5,"y":0.5,"a":0.8925,"m":0,"n":0,"r":0,"g":0,"o":0.5,"t":0.5,"e":0.5},"t2":{"c":[0,0,0],"x":0.5,"y":0.5,"a":0.8925,"m":0,"n":0,"r":0,"g":0,"o":0.5,"t":0.5,"e":0.5}},{"p":[1.081172,-0.3042736,-0.2504783],"r":[359.5366,267.6718,336.4127],"s":[0.39228,1.542406,0.01186222],"c":[0.3333332,0.2634919,0.1111109],"b":["when grabbed then become 1 in 0.5s","when starts then play object falling"],"t1":{"c":[0,0,0],"x":0.5,"y":0.5,"a":0.8925,"m":0,"n":0,"r":0,"g":0,"o":0.5,"t":0.5,"e":0.5},"t2":{"c":[0,0,0],"x":0.5,"y":0.5,"a":0.8925,"m":0,"n":0,"r":0,"g":0,"o":0.5,"t":0.5,"e":0.5}}]}]}