{"v":5,"a":[2,16],"p":[{"b":17,"t":2,"pr":40,"s":[{"p":[0,0,0],"r":[0,0,0],"s":[0.005000003,0.005000005,0.005000005],"c":[1,0.6857142,0],"b":["when starts then play heavy explosion","when starts then play distant explosion with surround ","when starts then become next"],"pr":{"c":[1,0.6857142,0],"m":0.25,"a":0.05473328,"s":0,"z":0.35,"g":0.5,"h":0.830368}},{"p":[0,0,0],"r":[0,0,0],"s":[0.2359085,0.2359086,0.2359086],"c":[1,0.6857142,0],"b":["when starts then become untweened next"],"pr":{"c":[1,0.6857142,0],"m":0.25,"a":0.25,"s":0.15,"z":0.35,"g":0.5,"h":0.830368}},{"p":[0,0,0],"r":[0,0,0],"s":[0.005,0.005,0.005],"c":[1,0.6857142,0],"b":["when starts then become next in 0.5s","when starts then turn invisible"],"pr":{"c":[1,0.6857142,0],"m":0.25,"a":0,"s":0.15,"z":0.35,"g":0.5,"h":0.830368}},{"p":[0,0,0],"r":[0,0,0],"s":[0.005000003,0.005000005,0.005000005],"c":[1,0.6857142,0],"b":["when starts then become next in 5s"],"pr":{"c":[1,0.6857142,0],"m":0.25,"a":0.6044769,"s":0,"z":0.4076538,"g":0.637207,"h":0.8422546}},{"p":[0,0,0],"r":[0,0,0],"s":[0.005,0.005,0.005],"c":[1,0.6857142,0],"b":["when starts then become next in 2s"],"pr":{"c":[1,0.6857142,0],"m":0.25,"a":0,"s":0.15,"z":0.35,"g":0.5,"h":0.830368}},{"p":[0,0,0],"r":[0,0,0],"s":[0.005,0.005,0.005],"c":[1,0.6857142,0],"b":["when starts then destroy all parts"],"pr":{"c":[1,0.6857142,0],"m":0.25,"a":0,"s":0.15,"z":0.35,"g":0.5,"h":0.830368}}]}]}