{"v":6,"p":[{"s":[{"p":[0,0,0],"r":[0,0,0],"s":[0.1750001,0.1750001,0.1750003],"c":[1,1,1],"b":["swhen told by any launch then set voice male -5 pitch 0.7 speed","swhen told by any launch  then say juggernaut demigod chocolate in .5s","when told by any launch  then become next in 0.2s"]},{"p":[0,0,0],"r":[0,0,0],"s":[0.1750001,0.1750001,0.1750003],"c":[1,1,1],"b":["when starts then set voice male -5 pitch 0.7 speed","when starts  then say juggernaut demigod chocolate","when starts then become next"]}]}]}