{"v":7,"a":[2,22,16],"p":[{"b":4,"a":[39],"s":[{"p":[0,0,0],"r":[0,0,1.067217E-06],"s":[0.03076633,0.02951622,0.09930304],"c":[1,1,1],"b":["when touched then become untweened next in 0","when starts then set voice male 500% 10 pitch -5 speed"]},{"p":[0,0,0],"r":[0,0,0],"s":[0.03076633,0.02951622,0.09930304],"c":[0.2910051,0.5555556,0.1851851],"b":["when starts then become untweened next in 0","when starts then say apple a day keeps the doctors away"]},{"p":[0,0,0],"r":[0,0,0],"s":[0.03076633,0.02951622,0.09930304],"c":[0.2910051,0.5555556,0.1851851],"b":["when starts then become untweened previous in 0","when starts then say apple apple apple apple apple apple apple apple apple apple apple apple"]}]}]}