{"n":"rusty shoulder r","v":7,"a":[7,12,18],"p":[{"t":21,"s":[{"p":[-3.580935E-07,3.728201E-08,0.01095319],"r":[-8.537735E-07,3.180554E-15,-4.268868E-07],"s":[0.001000002,0.001000001,0.001000001],"c":[0.222222,1,1],"b":["when starts then project with 100% reach, show line with 0.01 width","when told by body realbig then show line with 0.25 width","when told by body normalsize then show line with 0.01 width","when told by body small then show line with 0.001 width","when told by body realsmall then show line with 0.0001 width","when told by body large then show line with 0.1 width"]}]},{"b":4,"t":18,"a":[12,37],"i":[{"t":"5c7c66f25919c6054339fb76","p":[2.980232E-08,4.371141E-08,0.25],"r":[8.301862E-13,3.378279E-20,180]}],"s":[{"p":[0,0,0],"r":[0,0,4.268868E-07],"s":[0.04358784,0.04358768,0.04358791],"c":[1,1,1],"b":["when starts then all parts face nearest rusty right point","when told by nearby reset rustybot then all parts face nearest rusty right point"]}]},{"b":61,"a":[37,36],"s":[{"p":[0,0,0],"r":[0,0,4.268868E-07],"s":[0.001,0.001,0.001],"c":[1,0.5142855,0],"b":["when told by body armorup then become next in 0.5s, turn visible","when starts then turn off"]},{"p":[0,0,0],"r":[0,0,4.268868E-07],"s":[0.1014796,0.1014794,0.1014796],"c":[1,0.5142855,0],"b":["when told by body armordown then become previous in 0.5s","when told by nearby reset rustybot then become 1"]}]},{"b":61,"a":[37,36],"s":[{"p":[-9.622375E-09,4.082428E-08,0.2283059],"r":[-1.024528E-05,7.603076E-06,1.001791E-05],"s":[0.001,0.001,0.001],"c":[1,0.5142855,0],"b":["when told by body armorup then become next in 0.5s, turn visible","when starts then turn off"]},{"p":[-9.622375E-09,4.082428E-08,0.2283059],"r":[-1.024528E-05,7.603076E-06,1.001791E-05],"s":[0.1014797,0.1014831,0.04197906],"c":[1,0.5142855,0],"b":["when told by body armordown then become previous in 0.5s","when told by nearby reset rustybot then become 1"]}]},{"b":14,"a":[37,36],"s":[{"p":[-0.006902694,3.014031E-10,0.001727523],"r":[1.001791E-05,-2.442666E-12,89.99999],"s":[0.02470309,0.01049613,0.0009999959],"c":[0.444444,0.444444,0.444444],"b":["when told by body armorup then become next in 0.5s, turn visible","when starts then turn off"]},{"p":[-0.03747415,2.082724E-08,0.1164744],"r":[-1.024529E-05,-7.603077E-06,90],"s":[0.0247001,0.01049521,0.0389089],"c":[0.444444,0.444444,0.444444],"b":["when told by body armordown then become previous in 0.5s","when told by nearby reset rustybot then become 1"]}]},{"b":14,"a":[37,36],"s":[{"p":[1.546879E-10,0.0006631612,0.0005531312],"r":[0,0,6.157171E-14],"s":[0.02469211,0.01049403,0.0009999945],"c":[0.444444,0.444444,0.444444],"b":["when told by body armorup then become next in 0.5s, turn visible","when starts then turn off"]},{"p":[-4.909028E-09,0.03789505,0.1164744],"r":[-2.273715E-07,7.603076E-06,-8.727097E-13],"s":[0.02469169,0.01049367,0.03891036],"c":[0.444444,0.444444,0.444444],"b":["when told by body armordown then become previous in 0.5s","when told by nearby reset rustybot then become 1"]}]},{"b":14,"a":[37,36],"s":[{"p":[7.900098E-10,0.005240798,0.001897932],"r":[1.001791E-05,-1.252119E-12,180],"s":[0.02469597,0.01049659,0.0009999606],"c":[0.444444,0.444444,0.444444],"b":["when told by body armorup then become next in 0.5s, turn visible","when starts then turn off"]},{"p":[-4.909028E-09,-0.03789505,0.1164744],"r":[2.273715E-07,7.603076E-06,180],"s":[0.02469169,0.01049367,0.03891036],"c":[0.4444441,0.4444441,0.4444441],"b":["when told by body armordown then become previous in 0.5s","when told by nearby reset rustybot then become 1"]}]},{"b":14,"a":[37,36],"s":[{"p":[0.00353384,-4.929211E-10,0.00105226],"r":[1.001791E-05,-2.035555E-12,270],"s":[0.02470556,0.01049649,0.001000018],"c":[0.444444,0.444444,0.444444],"b":["when told by body armorup then become next in 0.5s, turn visible","when starts then turn off"]},{"p":[0.03747415,2.082724E-08,0.1164744],"r":[-1.024529E-05,7.603077E-06,270],"s":[0.0247001,0.01049521,0.0389089],"c":[0.444444,0.444444,0.444444],"b":["when told by body armordown then become previous in 0.5s","when told by nearby reset rustybot then become 1"]}]}]}