{"v":9,"a":[22,18,24,31],"bod":{"al": {"i":"5ca2c3fa282f953b244f40f9","p":[-0.0426821,-0.03681897,-0.06136035],"r":[353.4498,359.937,54.51099]},"ar": {"i":"5ca81cfbe3f3094e3375d62a","p":[0.0362592,-0.04004677,-0.05996915],"r":[354.5543,2.651209,294.3575]},"lt": {"i":"5ca82397e0132570a78960c6","p":[0.01841132,0.2501929,-0.00511393],"r":[356.2462,171.8586,0.8881176]}},"p":[{"b":60,"a":[36],"s":[{"p":[4.768372E-07,0.0590334,0.02907084],"r":[-6.157161E-14,1.001791E-05,1.001791E-05],"s":[0.01881286,0.01881286,0.01881286],"c":[0.5555556,0.3156961,0.0617279],"b":["when told by body mohawk then become untweened 2","when starts then turn invisible"]},{"p":[4.768372E-07,0.0590334,0.02907084],"r":[-6.157161E-14,1.001791E-05,1.001791E-05],"s":[0.05772959,0.1986467,0.2386077],"c":[0.5555556,0.3156962,0.06172792],"b":["when told by body greyh then become untweened 3","when told by body redh then become untweened 2","when told by body blondeh then become untweened 4","when told by body brownh then become untweened 5","when told by body blackh then become untweened 6","when told by body purpleh then become untweened 7","when told by body greenh then become untweened 8","when told by body pinkh then become untweened 9","when told by body blueh then become untweened 10","when told by body lightblueh then become untweened 11","when told by body short hair then become untweened 1","when told by body mohawk then become untweened 2","when told by body bald then become untweened 1","when told by body afro then become untweened 1","when told by body ponytail l then become untweened 1","when told by body ponytail s then become untweened 1","when told by body long hair then become untweened 1","when told by body medium hair then become untweened 1","when starts then turn visible"]},{"p":[4.768372E-07,0.0590334,0.02907084],"r":[-6.157161E-14,1.001791E-05,1.001791E-05],"s":[0.05772959,0.1986467,0.2386077],"c":[0.7777778,0.7777778,0.7777778],"b":["when told by body greyh then become untweened 3","when told by body redh then become untweened 2","when told by body blondeh then become untweened 4","when told by body brownh then become untweened 5","when told by body blackh then become untweened 6","when told by body purpleh then become untweened 7","when told by body greenh then become untweened 8","when told by body pinkh then become untweened 9","when told by body blueh then become untweened 10","when told by body lightblueh then become untweened 11","when told by body short hair then become untweened 1","when told by body mohawk then become untweened 2","when told by body bald then become untweened 1","when told by body afro then become untweened 1","when told by body ponytail l then become untweened 1","when told by body ponytail s then become untweened 1","when told by body long hair then become untweened 1","when told by body medium hair then become untweened 1"]},{"p":[4.768372E-07,0.0590334,0.02907084],"r":[-6.157161E-14,1.001791E-05,1.001791E-05],"s":[0.05772959,0.1986467,0.2386077],"c":[0.9873015,1,0.5555556],"b":["when told by body greyh then become untweened 3","when told by body redh then become untweened 2","when told by body blondeh then become untweened 4","when told by body brownh then become untweened 5","when told by body blackh then become untweened 6","when told by body purpleh then become untweened 7","when told by body greenh then become untweened 8","when told by body pinkh then become untweened 9","when told by body blueh then become untweened 10","when told by body lightblueh then become untweened 11","when told by body short hair then become untweened 1","when told by body mohawk then become untweened 2","when told by body bald then become untweened 1","when told by body afro then become untweened 1","when told by body ponytail l then become untweened 1","when told by body ponytail s then become untweened 1","when told by body long hair then become untweened 1","when told by body medium hair then become untweened 1"]},{"p":[4.768372E-07,0.0590334,0.02907084],"r":[-6.157161E-14,1.001791E-05,1.001791E-05],"s":[0.05772959,0.1986467,0.2386077],"c":[0.3333329,0.2402111,0.03703704],"b":["when told by body greyh then become untweened 3","when told by body redh then become untweened 2","when told by body blondeh then become untweened 4","when told by body brownh then become untweened 5","when told by body blackh then become untweened 6","when told by body purpleh then become untweened 7","when told by body greenh then become untweened 8","when told by body pinkh then become untweened 9","when told by body blueh then become untweened 10","when told by body lightblueh then become untweened 11","when told by body short hair then become untweened 1","when told by body mohawk then become untweened 2","when told by body bald then become untweened 1","when told by body afro then become untweened 1","when told by body ponytail l then become untweened 1","when told by body ponytail s then become untweened 1","when told by body long hair then become untweened 1","when told by body medium hair then become untweened 1"]},{"p":[4.768372E-07,0.0590334,0.02907084],"r":[-6.157161E-14,1.001791E-05,1.001791E-05],"s":[0.05772959,0.1986467,0.2386077],"c":[0,0,0],"b":["when told by body greyh then become untweened 3","when told by body redh then become untweened 2","when told by body blondeh then become untweened 4","when told by body brownh then become untweened 5","when told by body blackh then become untweened 6","when told by body purpleh then become untweened 7","when told by body greenh then become untweened 8","when told by body pinkh then become untweened 9","when told by body blueh then become untweened 10","when told by body lightblueh then become untweened 11","when told by body short hair then become untweened 1","when told by body mohawk then become untweened 2","when told by body bald then become untweened 1","when told by body afro then become untweened 1","when told by body ponytail l then become untweened 1","when told by body ponytail s then become untweened 1","when told by body long hair then become untweened 1","when told by body medium hair then become untweened 1"]},{"p":[4.768372E-07,0.0590334,0.02907084],"r":[-6.157161E-14,1.001791E-05,1.001791E-05],"s":[0.05772959,0.1986467,0.2386077],"c":[0.6285716,0,1],"b":["when told by body greyh then become untweened 3","when told by body redh then become untweened 2","when told by body blondeh then become untweened 4","when told by body brownh then become untweened 5","when told by body blackh then become untweened 6","when told by body purpleh then become untweened 7","when told by body greenh then become untweened 8","when told by body pinkh then become untweened 9","when told by body blueh then become untweened 10","when told by body lightblueh then become untweened 11","when told by body short hair then become untweened 1","when told by body mohawk then become untweened 2","when told by body bald then become untweened 1","when told by body afro then become untweened 1","when told by body ponytail l then become untweened 1","when told by body ponytail s then become untweened 1","when told by body long hair then become untweened 1","when told by body medium hair then become untweened 1"]},{"p":[4.768372E-07,0.0590334,0.02907084],"r":[-6.157161E-14,1.001791E-05,1.001791E-05],"s":[0.05772959,0.1986467,0.2386077],"c":[0.08888858,0.7777778,0],"b":["when told by body greyh then become untweened 3","when told by body redh then become untweened 2","when told by body blondeh then become untweened 4","when told by body brownh then become untweened 5","when told by body blackh then become untweened 6","when told by body purpleh then become untweened 7","when told by body greenh then become untweened 8","when told by body pinkh then become untweened 9","when told by body blueh then become untweened 10","when told by body lightblueh then become untweened 11","when told by body short hair then become untweened 1","when told by body mohawk then become untweened 2","when told by body bald then become untweened 1","when told by body afro then become untweened 1","when told by body ponytail l then become untweened 1","when told by body ponytail s then become untweened 1","when told by body long hair then become untweened 1","when told by body medium hair then become untweened 1"]},{"p":[4.768372E-07,0.0590334,0.02907084],"r":[-6.157161E-14,1.001791E-05,1.001791E-05],"s":[0.05772959,0.1986467,0.2386077],"c":[0.9714285,0,1],"b":["when told by body greyh then become untweened 3","when told by body redh then become untweened 2","when told by body blondeh then become untweened 4","when told by body brownh then become untweened 5","when told by body blackh then become untweened 6","when told by body purpleh then become untweened 7","when told by body greenh then become untweened 8","when told by body pinkh then become untweened 9","when told by body blueh then become untweened 10","when told by body lightblueh then become untweened 11","when told by body short hair then become untweened 1","when told by body mohawk then become untweened 2","when told by body bald then become untweened 1","when told by body afro then become untweened 1","when told by body ponytail l then become untweened 1","when told by body ponytail s then become untweened 1","when told by body long hair then become untweened 1","when told by body medium hair then become untweened 1"]},{"p":[4.768372E-07,0.0590334,0.02907084],"r":[-6.157161E-14,1.001791E-05,1.001791E-05],"s":[0.05772959,0.1986467,0.2386077],"c":[0,0.0571425,1],"b":["when told by body greyh then become untweened 3","when told by body redh then become untweened 2","when told by body blondeh then become untweened 4","when told by body brownh then become untweened 5","when told by body blackh then become untweened 6","when told by body purpleh then become untweened 7","when told by body greenh then become untweened 8","when told by body pinkh then become untweened 9","when told by body blueh then become untweened 10","when told by body lightblueh then become untweened 11","when told by body short hair then become untweened 1","when told by body mohawk then become untweened 2","when told by body bald then become untweened 1","when told by body afro then become untweened 1","when told by body ponytail l then become untweened 1","when told by body ponytail s then become untweened 1","when told by body long hair then become untweened 1","when told by body medium hair then become untweened 1"]},{"p":[4.768372E-07,0.0590334,0.02907084],"r":[-6.157161E-14,1.001791E-05,1.001791E-05],"s":[0.05772959,0.1986467,0.2386077],"c":[0,1,0.9142858],"b":["when told by body greyh then become untweened 3","when told by body redh then become untweened 2","when told by body blondeh then become untweened 4","when told by body brownh then become untweened 5","when told by body blackh then become untweened 6","when told by body purpleh then become untweened 7","when told by body greenh then become untweened 8","when told by body pinkh then become untweened 9","when told by body blueh then become untweened 10","when told by body lightblueh then become untweened 11","when told by body short hair then become untweened 1","when told by body mohawk then become untweened 2","when told by body bald then become untweened 1","when told by body afro then become untweened 1","when told by body ponytail l then become untweened 1","when told by body ponytail s then become untweened 1","when told by body long hair then become untweened 1","when told by body medium hair then become untweened 1"]}]}]}