{"v":9,"p":[{"a":[12],"s":[{"p":[1.248196,-1.658269,1.257619],"r":[344.1846,299.7198,85.43206],"s":[0.1750002,0.1750003,0.1750004],"c":[1,1,1],"b":["when told by nearby elelurch then become next in 1.3s"]},{"p":[1.248196,-1.658269,1.257619],"r":[344.1846,299.7198,85.43206],"s":[0.1750002,0.1750003,0.1750004],"c":[1,1,1],"b":["when starts then play breaking kicking in door with high-pitch 300","when starts then play explosion kickback crackle with low-pitch 300","when starts then play machine 24 with 1s skip low-pitch 400 0.5s delay"]}]}]}