{"v":9,"a":[2,3,31],"p":[{"b":166,"pr":25,"t1":43,"t2":42,"s":[{"p":[0,0,0],"r":[0,0,-1.707547E-06],"s":[0.009696022,0.03091798,0.008516353],"c":[0.4444443,0.2525572,0.04938262],"b":["when triggered then tell pressed "],"t1":{"c":[0,0,0],"x":0.5,"y":0.5,"a":0.8925,"m":0,"n":0,"r":0,"g":0,"o":0.5,"t":0.5,"e":0.5},"t2":{"c":[0.4444444,0.2525572,0.04938267],"x":0.5,"y":0.5,"a":0.8925,"m":0,"n":0,"r":0,"g":0,"o":0.5,"t":0.5,"e":0.5},"pr":{"c":[0.9714286,1,0],"m":0.468642,"a":0.25,"s":0.15,"z":0.25,"g":0.5,"h":0.25}}]},{"b":10,"a":[12],"s":[{"p":[-0.002663657,0.1459498,-0.0002096929],"r":[306.2241,67.03781,280.2536],"s":[0.0307472,0.03074691,0.03074716],"c":[1,1,1],"b":["when told pressed then say skadadel skadoodel your dick is now a noodle","when told pressed then become next"]},{"p":[-0.02834603,0.2107527,-0.01553478],"r":[301.5389,74.20848,266.0292],"s":[0.03074725,0.03074695,0.0307472],"c":[1,1,1],"b":["when told pressed then say ska daa ska deen get this shit off my screen","when told pressed then become 1"]}]}]}