{"v":9,"a":[7,21,40,44],"p":[{"b":5,"s":[{"p":[0,0.007954597,0],"r":[90,270,0],"s":[0.005111245,0.005111245,0.005111317],"c":[0,0,0]}]},{"b":18,"e":"12","s":[{"p":[-0.01319551,-0.001470566,0.1078762],"r":[90,-1.931869E-05,0],"s":[0.002174902,0.002174484,0.002174847],"c":[0,0,0]}]},{"b":18,"e":"6","s":[{"p":[-0.007500648,0.0004529953,-0.0853368],"r":[90,-9.659345E-06,0],"s":[0.001867204,0.001866594,0.001867154],"c":[0,0,0]}]},{"b":18,"e":"1","s":[{"p":[0.04013348,-0.0003767014,0.09483278],"r":[90,-9.659345E-06,0],"s":[0.001867398,0.001866606,0.001867451],"c":[0,0,0]}]},{"b":18,"e":"7","s":[{"p":[-0.0510416,0.003752708,-0.0704062],"r":[90,-1.931869E-05,0],"s":[0.001867727,0.001866898,0.001867448],"c":[0,0,0]}]},{"b":18,"e":"5","s":[{"p":[0.03712177,-0.001350403,-0.07325149],"r":[90,-1.931869E-05,0],"s":[0.002174655,0.002174478,0.002174673],"c":[0,0,0]}]},{"b":18,"e":"11","s":[{"p":[-0.06235218,-0.0005970001,0.0934931],"r":[90,-1.931869E-05,0],"s":[0.002174825,0.002174417,0.002174941],"c":[0,0,0]}]},{"b":18,"e":"4","s":[{"p":[0.06423855,-0.002755165,-0.05276096],"r":[90,-9.659345E-06,0],"s":[0.002175888,0.002174465,0.002176046],"c":[0,0,0]}]},{"b":18,"e":"10","s":[{"p":[-0.1019249,-0.003237724,0.0508337],"r":[90,-9.659345E-06,0],"s":[0.002176738,0.002174344,0.002176527],"c":[0,0,0]}]},{"b":18,"e":"2","s":[{"p":[0.07625008,0.0001516342,0.06246483],"r":[90,-1.931869E-05,0],"s":[0.002174778,0.002174487,0.002174802],"c":[0,0,0]}]},{"b":18,"e":"8","s":[{"p":[-0.08564758,0.003545761,-0.04160023],"r":[90,-1.931869E-05,0],"s":[0.002174907,0.002174526,0.002174993],"c":[0,0,0]}]},{"b":18,"e":"3","s":[{"p":[0.08819437,0.0007953644,0.0139966],"r":[90,-1.931869E-05,0],"s":[0.002174633,0.002174504,0.002174552],"c":[0,0,0]}]},{"b":18,"e":"9","s":[{"p":[-0.1003814,0.003954887,0.007159352],"r":[90,-9.659345E-06,0],"s":[0.002174651,0.002174502,0.00217457],"c":[0,0,0]}]},{"b":5,"s":[{"p":[0,-0.005944252,0],"r":[90,270,0],"s":[0.06247316,0.06247631,0.02745344],"c":[1,1,1],"b":["when starts then become untweened next"]},{"p":[0,-0.005944252,0],"r":[90,270,0],"s":[0.06247953,0.06249197,0.02745851],"c":[1,1,1],"b":["when starts then become next in 0.2s","when starts then is minute = [minute]"]}]},{"b":5,"s":[{"p":[0,-0.0146904,0],"r":[90,90,0],"s":[0.0893155,0.08931702,0.01689048],"c":[0,0.08888858,0.222222],"b":["when starts then become untweened next"]},{"p":[0,-0.0146904,0],"r":[90,90,0],"s":[0.0893155,0.08931702,0.01689048],"c":[0,0.08888858,0.222222],"b":["when starts then become untweened previous in 0.2s","when starts then is minute = [minute]","when starts then is second = [second]"]}]},{"b":5,"s":[{"p":[0,-0.00970459,0],"r":[90,270,0],"s":[0.07734337,0.07734583,0.01518319],"c":[1,1,1],"b":["when starts then is enddigit = [year] - (floor([year]/100) * 100)","when starts then become untweened next ","when starts then is month = [month]","when starts then is day = [day]"]},{"p":[0,-0.00970459,0],"r":[90,270,0],"s":[0.07734337,0.07734583,0.01518319],"c":[1,1,1],"b":["when starts then is doom = enddigit + floor(enddigit/4) - floor(enddigit/100) + floor(enddigit/400) + 2","when starts then become untweened next"]},{"p":[0,-0.00970459,0],"r":[90,270,0],"s":[0.07734337,0.07734583,0.01518319],"c":[1,1,1],"b":["when starts then is doomsday = mod(doom 7), become untweened next"]},{"p":[0,-0.00970459,0],"r":[90,270,0],"s":[0.07734337,0.07734583,0.01518319],"c":[1,1,1],"b":["when starts then is dststart = 14 - doomsday, is dstend = 7 - doomsday, become untweened next"]},{"p":[0,-0.00970459,0],"r":[90,270,0],"s":[0.07734337,0.07734583,0.01518319],"c":[1,1,1],"b":["when starts and is month < 3 or month = 12 then is not dst","when starts and is month > 3 and month < 11 then is dst","when starts and is month = 3 and day < dststart then is not dst","when starts and is month = 3 and day >= dststart then is dst","when starts and is month = 11 and day < dstend then is dst","when starts and is month = 11 and day >= dstend then is not dst","when starts then become untweened next"]},{"p":[0,-0.00970459,0],"r":[90,270,0],"s":[0.07734337,0.07734583,0.01518319],"c":[1,1,1],"b":["when starts and is dst then is hour = mod(([hour 12] + 20) 12)","when starts and is not dst then is hour = mod(([hour 12] + 19) 12)","when starts then become untweened next"]},{"p":[0,-0.00970459,0],"r":[90,270,0],"s":[0.07734337,0.07734583,0.01518319],"c":[1,1,1],"b":["when starts and is hour = 0 then is hour = 12","when starts then become untweened 1 in 1s"]}]},{"b":4,"a":[36],"s":[{"p":[0,0.01046753,0],"r":[0,30,90],"s":[0.0005338584,0.01200732,0.04278957],"c":[0,0,0],"b":["when any state is hour = 1 then become untweened 1","when any state is hour = 2 then become untweened 2","when any state is hour = 3 then become untweened 3","when any state is hour = 4 then become untweened 4","when any state is hour = 5 then become untweened 5","when any state is hour = 6 then become untweened 6","when any state is hour = 7 then become untweened 7","when any state is hour = 8 then become untweened 8","when any state is hour = 9 then become untweened 9","when any state is hour = 10 then become untweened 10","when any state is hour = 11 then become untweened 11","when any state is hour = 12 then become untweened 12"]},{"p":[0,0.01046753,0],"r":[-2.219812E-05,60.00002,90],"s":[0.0005338609,0.01200726,0.04278964],"c":[0,0,0]},{"p":[0,0.01046753,0],"r":[-8.196227E-05,90,90],"s":[0.0005338546,0.01200724,0.04278924],"c":[0,0,0]},{"p":[0,0.01046753,0],"r":[5.122642E-06,120,90],"s":[0.0005338566,0.01200727,0.04278949],"c":[0,0,0]},{"p":[0,0.01046753,0],"r":[0,150,90],"s":[0.0005338572,0.01200728,0.04278965],"c":[0,0,0]},{"p":[0,0.01046753,0],"r":[2.414837E-06,180,90],"s":[0.0005338585,0.01200731,0.04278957],"c":[0,0,0]},{"p":[0,0.01046753,0],"r":[-5.122642E-06,210,89.99998],"s":[0.0005338596,0.01200741,0.04278972],"c":[0,0,0]},{"p":[0,0.01046753,0],"r":[0,240,90],"s":[0.0005338613,0.0120075,0.04278976],"c":[0,0,0]},{"p":[0,0.01046753,0],"r":[0,270,90],"s":[0.0005338562,0.01200738,0.04278938],"c":[0,0,0]},{"p":[0,0.01046753,0],"r":[1.707547E-05,300,90.00003],"s":[0.0005338604,0.01200742,0.04278951],"c":[0,0,0]},{"p":[0,0.01046753,0],"r":[-9.391511E-06,330,90.00002],"s":[0.0005338566,0.01200734,0.04278942],"c":[0,0,0]},{"p":[0,0.01046753,0],"r":[6.350153E-06,-1.569644E-05,90],"s":[0.0005338601,0.01200731,0.04278945],"c":[0,0,0]}]},{"b":4,"a":[36],"s":[{"p":[0,0.0138216,0],"r":[0,6.000002,0],"s":[0.003601348,0.0005339211,0.07501128],"c":[1,0,0.3428572],"b":["when any state is second > 30 then become untweened 31","when any state is second = 1 then become untweened 1","when any state is second = 2 then become untweened 2","when any state is second = 3 then become untweened 3","when any state is second = 4 then become untweened 4","when any state is second = 5 then become untweened 5","when any state is second = 6 then become untweened 6","when any state is second = 7 then become untweened 7","when any state is second = 8 then become untweened 8","when any state is second = 9 then become untweened 9","when any state is second = 10 then become untweened 10","when any state is second = 11 then become untweened 11","when any state is second = 12 then become untweened 12","when any state is second = 13 then become untweened 13","when any state is second = 14 then become untweened 14","when any state is second = 15 then become untweened 15","when any state is second = 16 then become untweened 16","when any state is second = 17 then become untweened 17","when any state is second = 18 then become untweened 18","when any state is second = 19 then become untweened 19","when any state is second = 20 then become untweened 20","when any state is second = 21 then become untweened 21","when any state is second = 22 then become untweened 22","when any state is second = 23 then become untweened 23","when any state is second = 24 then become untweened 24","when any state is second = 25 then become untweened 25","when any state is second = 26 then become untweened 26","when any state is second = 27 then become untweened 27","when any state is second = 28 then become untweened 28","when any state is second = 29 then become untweened 29","when any state is second = 30 then become untweened 30"]},{"p":[0,0.0138216,0],"r":[7.139494E-07,12,-6.792773E-06],"s":[0.003601348,0.0005339247,0.07501192],"c":[1,0,0.3428572]},{"p":[0,0.0138216,0],"r":[1.068477E-06,18.00001,-6.746098E-06],"s":[0.003601347,0.0005339254,0.07501219],"c":[1,0,0.3428571]},{"p":[0,0.0138216,0],"r":[2.718361E-05,23.99998,-4.696117E-06],"s":[0.003601341,0.000533924,0.07501177],"c":[1,0,0.3428571]},{"p":[0,0.0138216,0],"r":[1.013302E-05,29.99998,-1.142713E-05],"s":[0.003601341,0.0005339234,0.07501172],"c":[1,0,0.3428571]},{"p":[0,0.0138216,0],"r":[1.079917E-05,35.99998,-8.198278E-08],"s":[0.003601353,0.0005339266,0.07501234],"c":[1,0,0.342857]},{"p":[0,0.0138216,0],"r":[1.605437E-05,41.99998,-8.469552E-06],"s":[0.003601342,0.0005339242,0.07501166],"c":[1,0,0.342857]},{"p":[0,0.0138216,0],"r":[1.421018E-05,48,1.006507E-05],"s":[0.003601349,0.0005339245,0.07501173],"c":[1,0,0.3428569]},{"p":[0,0.0138216,0],"r":[1.676478E-05,54,4.709231E-06],"s":[0.003601359,0.0005339251,0.07501191],"c":[1,0,0.3428569]},{"p":[0,0.0138216,0],"r":[1.109084E-05,60,6.403302E-06],"s":[0.003601346,0.0005339214,0.07501137],"c":[1,0,0.3428569]},{"p":[0,0.0138216,0],"r":[5.72828E-06,65.99998,3.719987E-06],"s":[0.00360135,0.000533924,0.07501154],"c":[1,0,0.3428568]},{"p":[0,0.0138216,0],"r":[1.511052E-06,72.00003,9.540424E-06],"s":[0.003601372,0.000533923,0.07501195],"c":[1,0,0.3428568]},{"p":[0,0.0138216,0],"r":[1.009676E-06,78.00001,9.606431E-06],"s":[0.00360137,0.0005339242,0.07501194],"c":[1,0,0.3428568]},{"p":[0,0.0138216,0],"r":[3.806864E-06,84.00002,3.427717E-06],"s":[0.003601364,0.0005339238,0.07501169],"c":[1,0,0.3428567]},{"p":[0,0.0138216,0],"r":[9.659344E-06,90.00003,9.659349E-06],"s":[0.003601324,0.000533921,0.07501091],"c":[1,0,0.3428566]},{"p":[0,0.0138216,0],"r":[-5.055342E-07,96.00004,9.646108E-06],"s":[0.00360136,0.0005339234,0.07501154],"c":[1,0,0.3428566]},{"p":[0,0.0138216,0],"r":[-1.009676E-06,102,9.606431E-06],"s":[0.003601378,0.0005339242,0.0750118],"c":[1,0,0.3428566]},{"p":[0,0.0138216,0],"r":[-1.511054E-06,108,9.540423E-06],"s":[0.003601416,0.0005339306,0.07501364],"c":[1,0,0.3428565]},{"p":[0,0.0138216,0],"r":[-9.448267E-06,114,-2.008291E-06],"s":[0.003601397,0.0005339292,0.07501305],"c":[1,0,0.3428565]},{"p":[0,0.0138216,0],"r":[-1.225712E-05,120,6.090799E-06],"s":[0.003601385,0.0005339279,0.07501299],"c":[1,0,0.3428564]},{"p":[0,0.0138216,0],"r":[6.201682E-06,126,1.217149E-05],"s":[0.003601404,0.0005339286,0.07501321],"c":[1,0,0.3428564]},{"p":[0,0.0138216,0],"r":[1.247938E-05,132,-5.556176E-06],"s":[0.003601402,0.000533929,0.07501303],"c":[1,0,0.3428564]},{"p":[0,0.0138216,0],"r":[2.943494E-05,138,-1.861513E-05],"s":[0.003601366,0.0005339259,0.07501276],"c":[1,0,0.3428563]},{"p":[0,0.0138216,0],"r":[-2.115265E-05,144,1.225918E-05],"s":[0.003601393,0.0005339292,0.07501318],"c":[1,0,0.3428563]},{"p":[0,0.0138216,0],"r":[-1.384197E-05,150,1.431564E-05],"s":[0.00360138,0.000533929,0.07501294],"c":[1,0,0.3428563]},{"p":[0,0.0138216,0],"r":[-1.565372E-06,156,9.061205E-06],"s":[0.003601394,0.000533929,0.07501312],"c":[1,0,0.3428563]},{"p":[0,0.0138216,0],"r":[-2.067305E-05,162.0001,2.229142E-05],"s":[0.003601393,0.0005339271,0.07501316],"c":[1,0,0.3428562]},{"p":[0,0.0138216,0],"r":[-2.502927E-05,168.0001,2.323409E-05],"s":[0.003601398,0.0005339296,0.07501329],"c":[1,0,0.3428562]},{"p":[0,0.0138216,0],"r":[-9.337598E-06,174.0001,1.758826E-05],"s":[0.00360139,0.00053393,0.07501308],"c":[1,0,0.3428561]},{"p":[0,0.0138216,0],"r":[-1.195285E-05,180.0001,1.707546E-05],"s":[0.0036014,0.000533929,0.07501325],"c":[1,0,0.3428561]},{"p":[0,-0.0168705,0],"r":[-5.122642E-06,180,-3.816666E-13],"s":[0.003601442,0.0005339363,0.07501636],"c":[1,0,0.3428561]}]},{"b":4,"a":[36],"s":[{"p":[0,0.008050919,0],"r":[0,6.000002,0],"s":[0.006899738,0.0005338719,0.07500608],"c":[0,0,0],"b":["when any state is minute > 30 then become untweened 31","when any state is minute = 1 then become untweened 1","when any state is minute = 2 then become untweened 2","when any state is minute = 3 then become untweened 3","when any state is minute = 4 then become untweened 4","when any state is minute = 5 then become untweened 5","when any state is minute = 6 then become untweened 6","when any state is minute = 7 then become untweened 7","when any state is minute = 8 then become untweened 8","when any state is minute = 9 then become untweened 9","when any state is minute = 10 then become untweened 10","when any state is minute = 11 then become untweened 11","when any state is minute = 12 then become untweened 12","when any state is minute = 13 then become untweened 13","when any state is minute = 14 then become untweened 14","when any state is minute = 15 then become untweened 15","when any state is minute = 16 then become untweened 16","when any state is minute = 17 then become untweened 17","when any state is minute = 18 then become untweened 18","when any state is minute = 19 then become untweened 19","when any state is minute = 20 then become untweened 20","when any state is minute = 21 then become untweened 21","when any state is minute = 22 then become untweened 22","when any state is minute = 23 then become untweened 23","when any state is minute = 24 then become untweened 24","when any state is minute = 25 then become untweened 25","when any state is minute = 26 then become untweened 26","when any state is minute = 27 then become untweened 27","when any state is minute = 28 then become untweened 28","when any state is minute = 29 then become untweened 29","when any state is minute = 30 then become untweened 30"]},{"p":[0,0.008050919,0],"r":[7.139494E-07,12,-6.792773E-06],"s":[0.006899746,0.0005338756,0.0750067],"c":[0,0,0]},{"p":[0,0.008050919,0],"r":[1.068477E-06,18.00001,-6.746098E-06],"s":[0.006899734,0.0005338764,0.07500696],"c":[0,0,0]},{"p":[0,0.008050919,0],"r":[2.718361E-05,23.99998,-4.696117E-06],"s":[0.006899726,0.0005338748,0.07500669],"c":[0,0,0]},{"p":[0,0.008050919,0],"r":[1.013302E-05,29.99998,-1.142713E-05],"s":[0.00689972,0.0005338741,0.07500657],"c":[0,0,0]},{"p":[0,0.008050919,0],"r":[6.495896E-06,36.00002,2.110645E-06],"s":[0.006899724,0.0005338747,0.07500643],"c":[0,0,0]},{"p":[0,0.008050919,0],"r":[1.275306E-05,42,4.895442E-06],"s":[0.006899739,0.0005338755,0.07500666],"c":[0,0,0]},{"p":[0,0.008050919,0],"r":[2.322795E-05,48,6.603465E-06],"s":[0.006899749,0.0005338757,0.07500681],"c":[0,0,0]},{"p":[0,0.008050919,0],"r":[2.361124E-05,54,8.197678E-06],"s":[0.00689974,0.0005338747,0.07500641],"c":[0,0,0]},{"p":[0,0.008050919,0],"r":[1.109084E-05,60,6.403302E-06],"s":[0.006899733,0.0005338725,0.07500622],"c":[0,0,0]},{"p":[0,0.008050919,0],"r":[5.72828E-06,65.99998,3.719987E-06],"s":[0.006899739,0.0005338747,0.07500646],"c":[0,0,0]},{"p":[0,0.008050919,0],"r":[8.504348E-06,71.99999,-2.263808E-06],"s":[0.00689976,0.0005338753,0.07500663],"c":[0,0,0]},{"p":[0,0.008050919,0],"r":[5.308054E-06,78,4.298377E-06],"s":[0.006899784,0.0005338763,0.07500679],"c":[0,0,0]},{"p":[0,0.008050919,0],"r":[-1.04044E-05,84.00002,-1.396363E-05],"s":[0.006899761,0.0005338729,0.07500643],"c":[0,0,0]},{"p":[0,0.008050919,0],"r":[0,90,0],"s":[0.006899798,0.0005338763,0.07500698],"c":[0,0,0]},{"p":[0,0.008050919,0],"r":[5.055334E-07,96.00002,-9.646108E-06],"s":[0.006899747,0.0005338726,0.07500624],"c":[0,0,0]},{"p":[0,0.008050919,0],"r":[1.009676E-06,102,-9.606431E-06],"s":[0.006899795,0.0005338751,0.07500658],"c":[0,0,0]},{"p":[0,0.008050919,0],"r":[1.511054E-06,108,-9.540423E-06],"s":[0.006899821,0.0005338768,0.07500711],"c":[0,0,0]},{"p":[0,0.008050919,0],"r":[-8.221676E-06,114,-2.520103E-05],"s":[0.006899786,0.0005338747,0.07500648],"c":[0,0,0]},{"p":[0,0.008050919,0],"r":[-6.129707E-08,120,-1.376655E-05],"s":[0.006899806,0.0005338768,0.07500672],"c":[0,0,0]},{"p":[0,0.008050919,0],"r":[2.771548E-05,126,-2.082923E-05],"s":[0.006899805,0.0005338751,0.07500675],"c":[0,0,0]},{"p":[0,0.008050919,0],"r":[2.495875E-05,132,-1.111235E-05],"s":[0.006899802,0.0005338751,0.07500665],"c":[0,0,0]},{"p":[0,0.008050919,0],"r":[2.943494E-05,138,-1.861513E-05],"s":[0.006899735,0.0005338726,0.07500646],"c":[0,0,0]},{"p":[0,0.008050919,0],"r":[-5.358593E-06,144,-5.440575E-06],"s":[0.006899786,0.0005338755,0.07500662],"c":[0,0,0]},{"p":[0,0.008050919,0],"r":[-4.18262E-06,150,-2.414836E-06],"s":[0.006899797,0.0005338751,0.07500662],"c":[0,0,0]},{"p":[0,0.008050919,0],"r":[3.550189E-07,156,1.670233E-06],"s":[0.006899828,0.0005338751,0.07500687],"c":[0,0,0]},{"p":[0,0.008050919,0],"r":[-1.065339E-05,162,-1.770333E-06],"s":[0.006899861,0.0005338772,0.07500723],"c":[0,0,0]},{"p":[0,0.008050919,0],"r":[0,168,0],"s":[0.006899793,0.0005338753,0.07500685],"c":[0,0,0],"b":["",""]},{"p":[0,0.008050919,0],"r":[0,174,0],"s":[0.006899708,0.0005338717,0.07500609],"c":[0,0,0]},{"p":[0,0.008050919,0],"r":[-1.366038E-05,180,3.415094E-06],"s":[0.006899799,0.0005338751,0.07500665],"c":[0,0,0]},{"p":[0.003608704,0,0],"r":[-5.122642E-06,180,-3.816666E-13],"s":[0.006900042,0.0005338906,0.07500803],"c":[0,0,0]}]},{"b":4,"a":[36],"s":[{"p":[0,0.0138216,0],"r":[2.159289E-06,186,2.405163E-05],"s":[0.003601416,0.0005339336,0.07501394],"c":[1,0,0.342856],"b":["when any state is second < 31 then become untweened 31","when any state is second = 31 then become untweened 1","when any state is second = 32 then become untweened 2","when any state is second = 33 then become untweened 3","when any state is second = 34 then become untweened 4","when any state is second = 35 then become untweened 5","when any state is second = 36 then become untweened 6","when any state is second = 37 then become untweened 7","when any state is second = 38 then become untweened 8","when any state is second = 39 then become untweened 9","when any state is second = 40 then become untweened 10","when any state is second = 41 then become untweened 11","when any state is second = 42 then become untweened 12","when any state is second = 43 then become untweened 13","when any state is second = 44 then become untweened 14","when any state is second = 45 then become untweened 15","when any state is second = 46 then become untweened 16","when any state is second = 47 then become untweened 17","when any state is second = 48 then become untweened 18","when any state is second = 49 then become untweened 19","when any state is second = 50 then become untweened 20","when any state is second = 51 then become untweened 21","when any state is second = 52 then become untweened 22","when any state is second = 53 then become untweened 23","when any state is second = 54 then become untweened 24","when any state is second = 55 then become untweened 25","when any state is second = 56 then become untweened 26","when any state is second = 57 then become untweened 27","when any state is second = 58 then become untweened 28","when any state is second = 59 then become untweened 29","when any state is second = 0 then become untweened 30"]},{"p":[0,0.0138216,0],"r":[-1.134676E-05,192,2.627865E-05],"s":[0.003601475,0.000533937,0.07501474],"c":[1,0,0.3428559]},{"p":[0,0.0138216,0],"r":[-1.669763E-05,198,1.810134E-05],"s":[0.003601491,0.0005339374,0.07501487],"c":[1,0,0.3428559]},{"p":[0,0.0138216,0],"r":[-5.680302E-06,204,2.672373E-05],"s":[0.003601479,0.0005339357,0.07501478],"c":[1,0,0.3428559]},{"p":[0,0.0138216,0],"r":[-1.190081E-05,210,1.802458E-05],"s":[0.003601481,0.0005339389,0.07501467],"c":[1,0,0.3428558]},{"p":[0,0.0138216,0],"r":[-6.331934E-06,216,1.948769E-05],"s":[0.003601454,0.0005339354,0.07501447],"c":[1,0,0.3428558]},{"p":[0,0.0138216,0],"r":[-1.861514E-05,222,2.943493E-05],"s":[0.003601497,0.0005339387,0.07501488],"c":[1,0,0.3428558]},{"p":[0,0.0138216,0],"r":[-3.953271E-05,228,4.828627E-06],"s":[0.003601467,0.0005339368,0.07501447],"c":[1,0,0.3428558]},{"p":[0,0.0138216,0],"r":[-4.417961E-05,234,-1.484493E-05],"s":[0.003601476,0.0005339367,0.07501456],"c":[1,0,0.3428557]},{"p":[0,0.0138216,0],"r":[-4.330168E-06,240,2.116045E-05],"s":[0.003601475,0.0005339367,0.07501449],"c":[1,0,0.3428557]},{"p":[0,0.0138216,0],"r":[-6.723929E-06,245.9999,1.192156E-05],"s":[0.00360145,0.000533936,0.0750142],"c":[1,0,0.3428557]},{"p":[0,0.0138216,0],"r":[1.036077E-06,251.9999,7.527522E-07],"s":[0.003601449,0.0005339363,0.07501414],"c":[1,0,0.3428556]},{"p":[0,0.0138216,0],"r":[3.96662E-06,257.9999,-5.576705E-06],"s":[0.003601442,0.0005339336,0.07501414],"c":[1,0,0.3428556]},{"p":[0,0.0138216,0],"r":[1.075644E-05,263.9999,4.942099E-07],"s":[0.003601462,0.0005339363,0.07501456],"c":[1,0,0.3428555]},{"p":[0,0.0138216,0],"r":[-1.207419E-06,269.9999,-1.207417E-06],"s":[0.003601454,0.0005339365,0.07501427],"c":[1,0,0.3428555]},{"p":[0,0.0138216,0],"r":[1.472193E-05,275.9999,-4.064769E-06],"s":[0.00360145,0.0005339365,0.07501446],"c":[1,0,0.3428555]},{"p":[0,0.0138216,0],"r":[9.606432E-06,281.9999,1.009669E-06],"s":[0.003601451,0.0005339359,0.07501455],"c":[1,0,0.3428554]},{"p":[0,0.0138216,0],"r":[8.784902E-06,287.9999,6.281259E-06],"s":[0.00360145,0.0005339363,0.07501432],"c":[1,0,0.3428554]},{"p":[0,0.0138216,0],"r":[9.448268E-06,293.9999,2.008284E-06],"s":[0.003601448,0.0005339356,0.07501425],"c":[1,0,0.3428554]},{"p":[0,0.0138216,0],"r":[4.232089E-05,299.9999,-8.660362E-06],"s":[0.003601435,0.0005339358,0.07501435],"c":[1,0,0.3428553]},{"p":[0,0.0138216,0],"r":[4.593293E-06,305.9999,1.492447E-06],"s":[0.003601441,0.0005339357,0.07501455],"c":[1,0,0.3428553]},{"p":[0,0.0138216,0],"r":[-1.730796E-06,311.9999,4.50889E-06],"s":[0.003601445,0.0005339365,0.07501462],"c":[1,0,0.3428553]},{"p":[0,0.0138216,0],"r":[8.34093E-06,317.9999,-6.859855E-06],"s":[0.003601439,0.000533938,0.07501455],"c":[1,0,0.3428552]},{"p":[0,0.0138216,0],"r":[8.688517E-06,323.9999,-6.413921E-06],"s":[0.003601424,0.0005339354,0.07501426],"c":[1,0,0.3428552]},{"p":[0,0.0138216,0],"r":[1.767788E-06,329.9999,6.597455E-06],"s":[0.003601434,0.0005339367,0.07501462],"c":[1,0,0.3428552]},{"p":[0,0.0138216,0],"r":[6.680932E-06,335.9999,-1.420082E-06],"s":[0.003601436,0.000533937,0.07501449],"c":[1,0,0.3428552]},{"p":[0,0.0138216,0],"r":[1.242371E-05,341.9999,-8.883064E-06],"s":[0.00360143,0.0005339342,0.07501429],"c":[1,0,0.3428551]},{"p":[0,0.0138216,0],"r":[3.307142E-05,347.9999,-1.206074E-05],"s":[0.003601423,0.000533935,0.07501435],"c":[1,0,0.3428551]},{"p":[0,0.0138216,0],"r":[1.005251E-05,353.9999,-3.946619E-06],"s":[0.00360143,0.0005339365,0.07501441],"c":[1,0,0.3428551]},{"p":[0,0.0138216,0],"r":[1.366037E-05,-6.83019E-05,-1.366039E-05],"s":[0.003601422,0.0005339359,0.07501462],"c":[1,0,0.342855]},{"p":[0,-0.01896572,0],"r":[0,0,-8.537737E-06],"s":[0.003601693,0.0005339741,0.07501854],"c":[1,0,0.342855]}]},{"b":4,"a":[36],"s":[{"p":[0,0.008050919,0],"r":[-1.283011E-05,186,1.642651E-05],"s":[0.006899728,0.0005338729,0.07500617],"c":[0,0,0],"b":["when any state is minute < 31 then become untweened 31","when any state is minute = 31 then become untweened 1","when any state is minute = 32 then become untweened 2","when any state is minute = 33 then become untweened 3","when any state is minute = 34 then become untweened 4","when any state is minute = 35 then become untweened 5","when any state is minute = 36 then become untweened 6","when any state is minute = 37 then become untweened 7","when any state is minute = 38 then become untweened 8","when any state is minute = 39 then become untweened 9","when any state is minute = 40 then become untweened 10","when any state is minute = 41 then become untweened 11","when any state is minute = 42 then become untweened 12","when any state is minute = 43 then become untweened 13","when any state is minute = 44 then become untweened 14","when any state is minute = 45 then become untweened 15","when any state is minute = 46 then become untweened 16","when any state is minute = 47 then become untweened 17","when any state is minute = 48 then become untweened 18","when any state is minute = 49 then become untweened 19","when any state is minute = 50 then become untweened 20","when any state is minute = 51 then become untweened 21","when any state is minute = 52 then become untweened 22","when any state is minute = 53 then become untweened 23","when any state is minute = 54 then become untweened 24","when any state is minute = 55 then become untweened 25","when any state is minute = 56 then become untweened 26","when any state is minute = 57 then become untweened 27","when any state is minute = 58 then become untweened 28","when any state is minute = 59 then become untweened 29","when any state is minute = 0 then become untweened 30"]},{"p":[0,0.008050919,0],"r":[-2.252017E-05,192,1.823647E-05],"s":[0.006899811,0.0005338747,0.07500706],"c":[0,0,0]},{"p":[0,0.008050919,0],"r":[-2.060492E-05,198,2.094015E-05],"s":[0.006899847,0.0005338771,0.07500695],"c":[0,0,0]},{"p":[0,0.008050919,0],"r":[-5.680302E-06,204,2.672373E-05],"s":[0.006899823,0.0005338748,0.07500681],"c":[0,0,0]},{"p":[0,0.008050919,0],"r":[-1.190081E-05,210,1.802458E-05],"s":[0.006899832,0.0005338774,0.07500682],"c":[0,0,0]},{"p":[0,0.008050919,0],"r":[-8.442576E-06,216,2.598358E-05],"s":[0.006899795,0.0005338759,0.0750066],"c":[0,0,0]},{"p":[0,0.008050919,0],"r":[-2.892047E-05,222,1.816296E-05],"s":[0.00689979,0.0005338748,0.07500689],"c":[0,0,0]},{"p":[0,0.008050919,0],"r":[-5.652097E-05,228,1.00325E-06],"s":[0.006899803,0.0005338763,0.07500666],"c":[0,0,0]},{"p":[0,0.008050919,0],"r":[-2.609628E-05,234,1.736608E-05],"s":[0.006899793,0.0005338743,0.07500657],"c":[0,0,0]},{"p":[0,0.008050919,0],"r":[-4.330168E-06,240,2.116045E-05],"s":[0.006899804,0.000533876,0.07500667],"c":[0,0,0]},{"p":[0,0.008050919,0],"r":[-6.723929E-06,245.9999,1.192156E-05],"s":[0.00689978,0.0005338753,0.07500637],"c":[0,0,0]},{"p":[0,0.008050919,0],"r":[-6.647922E-06,251.9999,1.205516E-05],"s":[0.006899752,0.0005338763,0.07500629],"c":[0,0,0]},{"p":[0,0.008050919,0],"r":[-1.327014E-06,257.9999,-1.074593E-06],"s":[0.006899749,0.0005338746,0.07500628],"c":[0,0,0]},{"p":[0,0.008050919,0],"r":[1.075644E-05,263.9999,4.942099E-07],"s":[0.006899791,0.0005338761,0.07500666],"c":[0,0,0]},{"p":[0,0.008050919,0],"r":[-1.207413E-06,269.9999,8.451929E-06],"s":[0.006899743,0.0005338734,0.07500628],"c":[0,0,0]},{"p":[0,0.008050919,0],"r":[-1.505276E-06,275.9999,8.535773E-06],"s":[0.006899782,0.0005338761,0.07500663],"c":[0,0,0]},{"p":[0,0.008050919,0],"r":[9.606432E-06,281.9999,1.009669E-06],"s":[0.006899769,0.0005338751,0.07500665],"c":[0,0,0]},{"p":[0,0.008050919,0],"r":[8.784902E-06,287.9999,6.281259E-06],"s":[0.00689977,0.0005338754,0.07500643],"c":[0,0,0]},{"p":[0,0.008050919,0],"r":[9.448268E-06,293.9999,2.008284E-06],"s":[0.006899769,0.0005338748,0.07500637],"c":[0,0,0]},{"p":[0,0.008050919,0],"r":[4.232089E-05,299.9999,-8.660362E-06],"s":[0.006899744,0.0005338748,0.07500652],"c":[0,0,0]},{"p":[0,0.008050919,0],"r":[1.377988E-05,305.9999,4.477341E-06],"s":[0.006899731,0.0005338724,0.07500607],"c":[0,0,0]},{"p":[0,0.008050919,0],"r":[-2.414295E-06,311.9999,1.976636E-05],"s":[0.006899766,0.000533875,0.07500687],"c":[0,0,0]},{"p":[0,0.008050919,0],"r":[4.895453E-06,317.9999,1.275306E-05],"s":[0.006899742,0.0005338748,0.07500643],"c":[0,0,0]},{"p":[0,0.008050919,0],"r":[4.221299E-06,323.9999,1.299179E-05],"s":[0.006899724,0.0005338747,0.07500628],"c":[0,0,0]},{"p":[0,0.008050919,0],"r":[-6.470449E-07,329.9999,1.078008E-05],"s":[0.006899743,0.0005338757,0.07500682],"c":[0,0,0]},{"p":[0,0.008050919,0],"r":[9.521097E-06,335.9999,1.194178E-05],"s":[0.006899735,0.0005338763,0.07500651],"c":[0,0,0]},{"p":[0,0.008050919,0],"r":[1.065339E-05,341.9999,1.770323E-06],"s":[0.00689973,0.0005338738,0.07500637],"c":[0,0,0]},{"p":[0,0.008050919,0],"r":[1.340706E-05,347.9999,-3.126102E-06],"s":[0.006899731,0.0005338768,0.07500676],"c":[0,0,0]},{"p":[0,0.008050919,0],"r":[1.005251E-05,353.9999,-3.946619E-06],"s":[0.006899726,0.0005338751,0.07500651],"c":[0,0,0]},{"p":[0,0.008050919,0],"r":[2.732075E-05,-9.562265E-05,-1.36604E-05],"s":[0.006899716,0.0005338751,0.07500665],"c":[0,0,0]},{"p":[0,-0.00292778,0],"r":[0,0,0],"s":[0.00690004,0.0005338968,0.07500948],"c":[0,0,0]}]}]}