{"editors":[{"id":"5802e36cd38bfe44219ceafa","name":"purple","isOwner":true},{"id":"57f85160800667411312ec10","name":"sparkyfun"},{"id":"580d282b64204f9413c6a897","name":"fykshun"},{"id":"5814297fffda8e8413fee32d","name":"the diaper sniper"},{"id":"581424bf181a23e70f6273e9","name":"chaybays"},{"id":"5811a99d6e58e0ae408271a5","name":"rannes"},{"id":"5815144a2598893813c45fe1","name":"cursive"},{"id":"58181d33160c0d921301ea5e","name":"lynk_wyland"},{"id":"581623cec256977f13c26895","name":"cdnguy31"},{"id":"57fc3b52d3cd9ce413772cc9","name":"jmiller"},{"id":"5815c211ab38c47713ae4abc","name":"swenkarssen"},{"id":"5817f778c723b53a13abbb74","name":"omegalevelgaming"},{"id":"57f6d45a8b2dbc371335b763","name":"graphics monkey"},{"id":"580ad19f5f83057137504a34","name":"nebby"},{"id":"58152678ef4df7591391416a","name":"zid"},{"id":"581bdfd3e6062479522de605","name":"thatguy"},{"id":"5803ecb0cecad656138adc91","name":"mr. melon shooter"}],"listEditors":[{"id":"580d282b64204f9413c6a897","name":"fykshun"}],"copiedFromAreas":[],"name":"work shope","creationDate":"2016-10-29T02:41:42.227Z","totalVisitors":85,"isZeroGravity":true,"hasFloatingDust":false,"isExcluded":false,"renameCount":0,"copiedCount":0,"isFavorited":false}