{"editors":[{"id":"5829bd78f83d7a125f4aa8ce","name":"neonrain","isOwner":true},{"id":"584aadbdde871e1013415cbc","name":"JoshBMDL"},{"id":"584aad9159a0b9d213c802a1","name":"PontusEdberg"},{"id":"5849ac39e1d59629111a4309","name":"gamedrix"},{"id":"5811a99d6e58e0ae408271a5","name":"rannes"},{"id":"582b9860509738f10fa7154e","name":"rebecca"}],"listEditors":[{"id":"5811a99d6e58e0ae408271a5","name":"rannes"}],"copiedFromAreas":[],"name":"sandbox for all","creationDate":"2016-12-09T13:24:56.755Z","totalVisitors":8,"isZeroGravity":true,"hasFloatingDust":false,"isExcluded":false,"renameCount":0,"copiedCount":0,"isFavorited":false}