{"editors":[{"id":"589c17888dd3810d10bfef4b","name":"xaviarsly","isOwner":true},{"id":"57fabb56749296a0149f5944","name":"frash"},{"id":"5cbcd17cfb0ce7267153a4f2","name":"crimsontaylor"}],"listEditors":[],"copiedFromAreas":[],"name":"the fairy fountain","description":"close your eyes and let her ease your paine","creationDate":"2017-04-11T06:13:41.608Z","totalVisitors":36,"parentAreaId":"58a1ecd55c0ebbd513686d5a","isZeroGravity":false,"hasFloatingDust":true,"isExcluded":false,"renameCount":1,"copiedCount":0,"isFavorited":false}