{"editors":[{"id":"591f93260fb0c53b101e298d","name":"other","isOwner":true},{"id":"58e9a890c00a79aa13da0da8","name":"redking"},{"id":"592381e9ac5bdcb823cd4084","name":"NobleArcher21"},{"id":"584b109442b0e21613ac80ab","name":"ctrl h"},{"id":"5810de65ac626721405bb671","name":"overvisor"},{"id":"593a3a49b51585d613fd6074","name":"Soju Son"},{"id":"593a3ab7b3c21dca13e46fc9","name":"RepairedKarma76"},{"id":"59361082f7fdcb693aea4ff3","name":"gnome mcbendyknees"},{"id":"581f44bd06205300559bbabe","name":"axel"},{"id":"580571c480ba33c9283bdf4c","name":"diamond tardis"},{"id":"59583e7da232542a100a6473","name":"kneesox"},{"id":"59529296035e063510ad9642","name":"Nekothyst"},{"id":"5a9c783cd91974f414cff608","name":"giodude"},{"id":"6215f5d846ecc005deac5723","name":"Vincent7186"}],"listEditors":[{"id":"59583e7da232542a100a6473","name":"kneesox"}],"copiedFromAreas":[],"name":"crystal garden","creationDate":"2017-05-26T04:37:31.608Z","totalVisitors":53,"isZeroGravity":false,"hasFloatingDust":false,"isExcluded":false,"renameCount":0,"copiedCount":0,"isFavorited":false}