{"editors":[{"id":"581f44bd06205300559bbabe","name":"axel","isOwner":true},{"id":"57f6d45a8b2dbc371335b763","name":"graphics monkey"},{"id":"59a8f959a28801a66205ac7f","name":"bunny"}],"listEditors":[],"copiedFromAreas":[{"id":"59b19637f45aa620104ef3de","name":"stretching room","creatorId":"581f44bd06205300559bbabe"}],"name":"beta stretch","creationDate":"2017-09-17T17:45:00.630Z","totalVisitors":15,"isZeroGravity":false,"hasFloatingDust":false,"isCopyable":false,"isExcluded":false,"renameCount":0,"copiedCount":1,"isFavorited":false}