{"editors":[{"id":"592b919246d5c023103f16f7","name":"atticus","isOwner":true},{"id":"587eae8fef27a2e9136bf231","name":"kamikaze squirrel"},{"id":"57f8c8c34f6a7c6a15b3cbe6","name":"nebula"},{"id":"5a771557cf009e9f1326cb11","name":"ben"},{"id":"5c74956fb22903781bd5bfe9","name":"Frank Blac"},{"id":"57f6856ed25a6ce10f2ae2b8","name":"xau"},{"id":"5a52c4ec0ab2ca8213eb6d94","name":"-hown_brash-"},{"id":"5d2ffcdd9dc6b5062ff86938","name":"chief"},{"id":"5c68f540636c692876543bb3","name":"soda"},{"id":"5b773104031d397ea66e1ace","name":"lenzic"},{"id":"5cebd5c9389bd60633f6d651","name":"chukklehed"}],"listEditors":[],"copiedFromAreas":[],"name":"- new home -","creationDate":"2017-11-04T01:49:32.464Z","totalVisitors":60,"isZeroGravity":false,"hasFloatingDust":false,"isCopyable":false,"isExcluded":false,"renameCount":3,"copiedCount":1,"isFavorited":false}