{"editors":[{"id":"5bc258681619fa61016cdea3","name":"Captain Spoopy Clay","isOwner":true},{"id":"591e3f9b138f05ac238d33bd","name":"sakhado"},{"id":"57f6856ed25a6ce10f2ae2b8","name":"xau"},{"id":"57f949279756413c12b2d3f2","name":"pen"}],"listEditors":[],"copiedFromAreas":[],"name":"captain clay's isle of the lost","creationDate":"2018-10-13T20:41:12.928Z","totalVisitors":17,"isZeroGravity":false,"hasFloatingDust":false,"isCopyable":false,"onlyOwnerSetsLocks":false,"isExcluded":false,"renameCount":1,"copiedCount":0,"isFavorited":false}