{"editors":[{"id":"5f25ff8a11766f3186f936b0","name":"mrblarhg","isOwner":true},{"id":"5bb6693c236557585f156458","name":"rustybot"},{"id":"5e53c3fb27f95755805207e0","name":"Seventy"},{"id":"5c77a5add3d4f8514e338203","name":"sloppy mcfloppy"}],"listEditors":[],"copiedFromAreas":[],"name":"mrblarhg's home","creationDate":"2020-08-01T23:49:30.934Z","totalVisitors":3,"isZeroGravity":false,"hasFloatingDust":false,"isCopyable":false,"onlyOwnerSetsLocks":false,"isExcluded":false,"renameCount":0,"copiedCount":0,"isFavorited":false}