{"editors":[{"id":"5f911606fe99c863186d3030","name":"alizard","isOwner":true},{"id":"6084d551872d1725a96aaa4f","name":"DJNightmares"},{"id":"5ceb1cfbba93cc529e907e7b","name":"dari"},{"id":"622ee49ba26e3a1f7c8dba0e","name":"seif1"},{"id":"5c68f540636c692876543bb3","name":"soda"},{"id":"5a1f4bf2de5ff9b61360fc10","name":"dr.tangerine"},{"id":"5a8704ccb30019e90fe5f631","name":"amplified"},{"id":"5982345787a8d7a613d36c22","name":"Michael97"},{"id":"600872f60002c1304ecbecff","name":"dfghiatus"},{"id":"643dc7e93cb7e7121907f479","name":"Shadow X"},{"id":"5e974d2aa28b185eb4eae1de","name":"scrapsavage"},{"id":"644f953fe94a4d05dcc053ee","name":"Niddle"},{"id":"5c77a5add3d4f8514e338203","name":"sloppy mcfloppy"}],"listEditors":[{"id":"6084d551872d1725a96aaa4f","name":"DJNightmares"}],"copiedFromAreas":[],"name":"lizard's home","description":"help","creationDate":"2020-10-22T05:17:58.193Z","totalVisitors":21,"isZeroGravity":false,"hasFloatingDust":false,"isCopyable":true,"onlyOwnerSetsLocks":true,"isExcluded":false,"renameCount":0,"copiedCount":0,"isFavorited":false}