{"editors":[{"id":"6176b8f156e8d005ddc45a15","name":"ea","isOwner":true},{"id":"6176b7b9a3d9d21bd27021bd","name":"TISSkipper"},{"id":"6176b872cd26271d46e30a1a","name":"STACKoverflow"},{"id":"6179481825f13a05e8fcc988","name":"KampFire"},{"id":"6179479b1536b91d3d8748c8","name":"Bjarke-dk"}],"listEditors":[],"copiedFromAreas":[{"id":"6177be4b177dd505e54746c1","name":"26-10-2021","creatorId":"6176b8f156e8d005ddc45a15"}],"name":"ea's home","creationDate":"2021-10-25T14:02:25.958Z","totalVisitors":7,"isZeroGravity":true,"hasFloatingDust":false,"isCopyable":true,"onlyOwnerSetsLocks":true,"isExcluded":false,"renameCount":0,"copiedCount":3,"isFavorited":false}